sugarcoat/__init__.py
sugarcoat/defaults.py
sugarcoat/endpoints.py
sugarcoat/request.py
sugarcoat/sugarcoat.py
tests/__init__.py
tests/support.py
tests/unit.py
sugarcoat_sdk-1.6.1.dist-info/METADATA
sugarcoat_sdk-1.6.1.dist-info/WHEEL
sugarcoat_sdk-1.6.1.dist-info/top_level.txt
sugarcoat_sdk-1.6.1.dist-info/RECORD
