Metadata-Version: 2.1
Name: sugarcoat-sdk
Version: 1.6.1
Summary: An SDK for the Sugarcoat API
Home-page: https://gitlab.com/sugarcoat/sugarcoat-python-sdk
Author: Jonathan Butler
Author-email: jonybutler@gmail.com
License: UNKNOWN
Platform: UNKNOWN
Classifier: Programming Language :: Python :: 3
Classifier: License :: OSI Approved :: MIT License
